wsgi_adapter/__init__.py
wsgi_adapter/handler.py
wsgi_adapter/response.py
lambda_wsgi_adapter-0.1.1.dist-info/LICENSE
lambda_wsgi_adapter-0.1.1.dist-info/METADATA
lambda_wsgi_adapter-0.1.1.dist-info/WHEEL
lambda_wsgi_adapter-0.1.1.dist-info/top_level.txt
lambda_wsgi_adapter-0.1.1.dist-info/RECORD
