Metadata-Version: 2.1
Name: lambda-wsgi-adapter
Version: 0.1.1
Summary: WSGI adapter for AWS Lambda
Home-page: https://github.com/spatocode/lambda-wsgi-adapter
Author: Ekene Izukanne
Author-email: ekeneizukanne@gmail.com
License: MIT
Keywords: wsgi aws lambda api gateway
Classifier: Programming Language :: Python
Classifier: License :: OSI Approved :: MIT License
Classifier: Operating System :: OS Independent
License-File: LICENSE
